ttxt_v2/__init__.py
ttxt_v2/connector/__init__.py
ttxt_v2/connector/binance/__init__.py
ttxt_v2/connector/binance/binance_auth.py
ttxt_v2/connector/binance/binance_futures.py
ttxt_v2/connector/bitget/__init__.py
ttxt_v2/connector/bitget/bitget.py
ttxt_v2/connector/bitget/bitget_auth.py
ttxt_v2/connector/bybit/__init__.py
ttxt_v2/connector/bybit/bybit.py
ttxt_v2/connector/bybit/bybit_auth.py
ttxt_v2/connector/bybit_fut/bybit_fut.py
ttxt_v2/connector/bybit_fut/bybit_fut_auth.py
ttxt_v2/connector/coinbase/__init__.py
ttxt_v2/connector/coinbase/coinbase.py
ttxt_v2/connector/coinbase/coinbase_auth.py
ttxt_v2/connector/connector_base.py
ttxt_v2/connector/connector_config.py
ttxt_v2/connector/connector_urls.py
ttxt_v2/connector/denormalizer_base.py
ttxt_v2/connector/gate_io/gate_auth.py
ttxt_v2/connector/gate_io/gate_io.py
ttxt_v2/connector/kucoin/__init__.py
ttxt_v2/connector/kucoin/kucoin.py
ttxt_v2/connector/kucoin/kucoin_auth.py
ttxt_v2/connector/mexc/__init__.py
ttxt_v2/connector/mexc/mexc.py
ttxt_v2/connector/mexc/mexc_auth.py
ttxt_v2/connector/normalizer_base.py
ttxt_v2/core/__init__.py
ttxt_v2/core/api/__init__.py
ttxt_v2/core/api/amend_order.py
ttxt_v2/core/api/asyncio_queue.py
ttxt_v2/core/api/base_client.py
ttxt_v2/core/api/base_queue.py
ttxt_v2/core/api/cancel_order.py
ttxt_v2/core/api/connector_status.py
ttxt_v2/core/api/create_order.py
ttxt_v2/core/api/enums.py
ttxt_v2/core/api/event.py
ttxt_v2/core/api/event_handler.py
ttxt_v2/core/api/header.py
ttxt_v2/core/api/instrument_info.py
ttxt_v2/core/api/kline.py
ttxt_v2/core/api/local_storage.py
ttxt_v2/core/api/market_data_recorder.py
ttxt_v2/core/api/market_data_replayer.py
ttxt_v2/core/api/market_trades.py
ttxt_v2/core/api/order_ack.py
ttxt_v2/core/api/order_update.py
ttxt_v2/core/api/orderbook.py
ttxt_v2/core/api/position_update.py
ttxt_v2/core/api/queue_actor.py
ttxt_v2/core/api/queue_consumer.py
ttxt_v2/core/api/queue_publisher.py
ttxt_v2/core/api/s3_storage.py
ttxt_v2/core/api/storage_backend.py
ttxt2-0.1.4.dist-info/LICENSE
ttxt2-0.1.4.dist-info/METADATA
ttxt2-0.1.4.dist-info/WHEEL
ttxt2-0.1.4.dist-info/RECORD
