Metadata-Version: 2.1
Name: ttxt2
Version: 0.1.4
Summary: Automated trading systems framework
License: MIT
Keywords: automated,trading,async,connector
Author: Ivan Yanakiev
Author-email: ivan.yanakiev@triremetrading.com
Requires-Python: >=3.11,<4.0
Classifier: License :: OSI Approved :: MIT License
Classifier: Programming Language :: Python :: 3
Classifier: Programming Language :: Python :: 3.11
Classifier: Programming Language :: Python :: 3.12
Requires-Dist: PyJWT (>=2.8.0,<3.0.0)
Requires-Dist: aiofiles (>=24.1.0,<25.0.0)
Requires-Dist: aiohttp (>=3.10.10,<4.0.0)
Requires-Dist: async-timeout (>=4.0.3,<5.0.0)
Requires-Dist: boto3 (>=1.35.56,<2.0.0)
Requires-Dist: colorlog (>=6.9.0,<7.0.0)
Requires-Dist: cryptography (>=42.0.5,<43.0.0)
Requires-Dist: dacite (>=1.8.1,<2.0.0)
Requires-Dist: msgpack (>=1.1.0,<2.0.0)
Requires-Dist: pydantic (>=2.3,<3.0)
Requires-Dist: python-dotenv (>=1.0.0,<2.0.0)
Requires-Dist: setuptools (>=74.1.2,<75.0.0)
